<?xml version="1.0" encoding="UTF-8"?>

<patch version="1.1000000238418579102" patchname="flashizn">
  <osc1fine value="0"/>
  <osc1coarse value="36"/>
  <osc1panDir value="36.600006103515625"/>
  <osc1vol value="-2.4501345157623291016"/>
  <osc1trngAmount value="0"/>
  <osc1pulseWidth value="0.36782249808311462402"/>
  <osc1oscWaveform value="0"/>
  <osc1OSCPitchModAmount1 value="11.993249893188476562"/>
  <osc1OSCPitchModAmount2 value="24"/>
  <osc1OSCPitchModSrc1 value="9"/>
  <osc1OSCPitchModSrc2 value="0"/>
  <osc1OSCPanModAmount1 value="71.84375"/>
  <osc1OSCPanModAmount2 value="50"/>
  <osc1OSCPanModSrc1 value="13"/>
  <osc1OSCPanModSrc2 value="0"/>
  <osc1OSCShapeModAmount1 value="0.29857811331748962402"/>
  <osc1OSCShapeModAmount2 value="0.5"/>
  <osc1OSCShapeModSrc1 value="9"/>
  <osc1OSCShapeModSrc2 value="0"/>
  <osc1OSCGainModAmount1 value="48"/>
  <osc1OSCGainModAmount2 value="48"/>
  <osc1GainModSrc1 value="0"/>
  <osc1GainModSrc2 value="0"/>
  <osc1Activation value="1"/>
  <osc2fine value="0"/>
  <osc2coarse value="36"/>
  <osc2panDir value="77.8125"/>
  <osc2vol value="-6.99554443359375"/>
  <osc2trngAmount value="0.53523439168930053711"/>
  <osc2pulseWidth value="0.66627842187881469727"/>
  <osc2oscWaveform value="1"/>
  <osc2OSCPitchModAmount1 value="11.934749603271484375"/>
  <osc2OSCPitchModAmount2 value="24"/>
  <osc2OSCPitchModSrc1 value="10"/>
  <osc2OSCPitchModSrc2 value="0"/>
  <osc2OSCPanModAmount1 value="33.43906402587890625"/>
  <osc2OSCPanModAmount2 value="50"/>
  <osc2OSCPanModSrc1 value="13"/>
  <osc2OSCPanModSrc2 value="0"/>
  <osc2OSCShapeModAmount1 value="0.5"/>
  <osc2OSCShapeModAmount2 value="0.5"/>
  <osc2OSCShapeModSrc1 value="0"/>
  <osc2OSCShapeModSrc2 value="0"/>
  <osc2OSCGainModAmount1 value="6.3569998741149902344"/>
  <osc2OSCGainModAmount2 value="48"/>
  <osc2GainModSrc1 value="9"/>
  <osc2GainModSrc2 value="0"/>
  <osc2Activation value="1"/>
  <osc3fine value="0"/>
  <osc3coarse value="0"/>
  <osc3panDir value="-8.4656219482421875"/>
  <osc3vol value="-23.8235931396484375"/>
  <osc3trngAmount value="0.68768751621246337891"/>
  <osc3pulseWidth value="0.5"/>
  <osc3oscWaveform value="1"/>
  <osc3OSCPitchModAmount1 value="35.951999664306640625"/>
  <osc3OSCPitchModAmount2 value="24"/>
  <osc3OSCPitchModSrc1 value="11"/>
  <osc3OSCPitchModSrc2 value="0"/>
  <osc3OSCPanModAmount1 value="23.621875762939453125"/>
  <osc3OSCPanModAmount2 value="50"/>
  <osc3OSCPanModSrc1 value="10"/>
  <osc3OSCPanModSrc2 value="0"/>
  <osc3OSCShapeModAmount1 value="0.5"/>
  <osc3OSCShapeModAmount2 value="0.5"/>
  <osc3OSCShapeModSrc1 value="0"/>
  <osc3OSCShapeModSrc2 value="0"/>
  <osc3OSCGainModAmount1 value="57.163501739501953125"/>
  <osc3OSCGainModAmount2 value="14.432999610900878906"/>
  <osc3GainModSrc1 value="14"/>
  <osc3GainModSrc2 value="9"/>
  <osc3Activation value="1"/>
  <env2envAttack value="0.63657778501510620117"/>
  <env2envDecay value="0.049999993294477462769"/>
  <env2envSustain value="1"/>
  <env2envRelease value="2.4001791477203369141"/>
  <env2envAttackShape value="1"/>
  <env2envDecayShape value="1"/>
  <env2envReleaseShape value="1"/>
  <env2ENVSpeedModAmount1 value="4"/>
  <env2ENVSpeedModAmount2 value="4"/>
  <env2ENVSpeedModSrc1 value="0"/>
  <env2ENVSpeedModSrc2 value="0"/>
  <env3envAttack value="5"/>
  <env3envDecay value="0.049999993294477462769"/>
  <env3envSustain value="1"/>
  <env3envRelease value="4.2122507095336914062"/>
  <env3envAttackShape value="1"/>
  <env3envDecayShape value="1"/>
  <env3envReleaseShape value="1"/>
  <env3ENVSpeedModAmount1 value="4"/>
  <env3ENVSpeedModAmount2 value="4"/>
  <env3ENVSpeedModSrc1 value="0"/>
  <env3ENVSpeedModSrc2 value="0"/>
  <envvolenvAttack value="1.284420013427734375"/>
  <envvolenvDecay value="0.092599049210548400879"/>
  <envvolenvSustain value="-6.19097900390625"/>
  <envvolenvRelease value="2.5050885677337646484"/>
  <envvolenvAttackShape value="0.52534401416778564453"/>
  <envvolenvDecayShape value="1"/>
  <envvolenvReleaseShape value="1"/>
  <envvolENVSpeedModAmount1 value="4"/>
  <envvolENVSpeedModAmount2 value="4"/>
  <envvolENVSpeedModSrc1 value="0"/>
  <envvolENVSpeedModSrc2 value="0"/>
  <lfo1lfoFadein value="0.075328417122364044189"/>
  <lfo1lfo1freq value="0.010448964312672615051"/>
  <lfo1LFOFreqModSrc1 value="0"/>
  <lfo1LFOFreqModSrc2 value="0"/>
  <lfo1LFOFreqModAmount1 value="2"/>
  <lfo1LFOFreqModAmount2 value="2"/>
  <lfo1tempoSyncSwitch value="0"/>
  <lfo1lfo1wave value="0"/>
  <lfo1notelength value="4"/>
  <lfo1LFOGainModSrc value="0"/>
  <lfo1lfoTriplet value="0"/>
  <lfo1lfoDottedLength value="0"/>
  <lfo2lfoFadein value="3.9149498939514160156"/>
  <lfo2lfo1freq value="11.4253082275390625"/>
  <lfo2LFOFreqModSrc1 value="0"/>
  <lfo2LFOFreqModSrc2 value="0"/>
  <lfo2LFOFreqModAmount1 value="2"/>
  <lfo2LFOFreqModAmount2 value="2"/>
  <lfo2tempoSyncSwitch value="0"/>
  <lfo2lfo1wave value="0"/>
  <lfo2notelength value="4"/>
  <lfo2LFOGainModSrc value="1"/>
  <lfo2lfoTriplet value="0"/>
  <lfo2lfoDottedLength value="0"/>
  <lfo3lfoFadein value="7.9626922607421875"/>
  <lfo3lfo1freq value="0.20445798337459564209"/>
  <lfo3LFOFreqModSrc1 value="0"/>
  <lfo3LFOFreqModSrc2 value="0"/>
  <lfo3LFOFreqModAmount1 value="2"/>
  <lfo3LFOFreqModAmount2 value="2"/>
  <lfo3tempoSyncSwitch value="1"/>
  <lfo3lfo1wave value="1"/>
  <lfo3notelength value="16"/>
  <lfo3LFOGainModSrc value="7"/>
  <lfo3lfoTriplet value="1"/>
  <lfo3lfoDottedLength value="0"/>
  <filter1FILTERType value="0"/>
  <filter1lpCutoff value="4840.99951171875"/>
  <filter1hpCutoff value="10"/>
  <filter1FILTERResonance value="3.1439061164855957031"/>
  <filter1FILTERLcModAmount1 value="1.3454999923706054688"/>
  <filter1FILTERLcModAmount2 value="4"/>
  <filter1FILTERLcModSrc1 value="10"/>
  <filter1FILTERLcModSrc2 value="0"/>
  <filter1FILTERHcModAmount1 value="4"/>
  <filter1FILTERHcModAmount2 value="4"/>
  <filter1FILTERHcModSrc1 value="0"/>
  <filter1FILTERHcModSrc2 value="0"/>
  <filter1FILTERResModAmount1 value="5"/>
  <filter1FILTERResModAmount2 value="5"/>
  <filter1FILTERResModSrc1 value="0"/>
  <filter1FILTERResModSrc2 value="0"/>
  <filter1filterActivation value="1"/>
  <filter2FILTERType value="3"/>
  <filter2lpCutoff value="20000"/>
  <filter2hpCutoff value="1423.999755859375"/>
  <filter2FILTERResonance value="2.2715620994567871094"/>
  <filter2FILTERLcModAmount1 value="4"/>
  <filter2FILTERLcModAmount2 value="4"/>
  <filter2FILTERLcModSrc1 value="0"/>
  <filter2FILTERLcModSrc2 value="0"/>
  <filter2FILTERHcModAmount1 value="1.4263750314712524414"/>
  <filter2FILTERHcModAmount2 value="4"/>
  <filter2FILTERHcModSrc1 value="11"/>
  <filter2FILTERHcModSrc2 value="0"/>
  <filter2FILTERResModAmount1 value="5"/>
  <filter2FILTERResModAmount2 value="5"/>
  <filter2FILTERResModSrc1 value="0"/>
  <filter2FILTERResModSrc2 value="0"/>
  <filter2filterActivation value="1"/>
  <seqPlaySyncHost value="0"/>
  <seqPlayMode value="0"/>
  <seqNumSteps value="8"/>
  <seqStepSpeed value="4"/>
  <seqNoteLength value="4"/>
  <seqTriplets value="0"/>
  <seqDottedLength value="0"/>
  <seqNote0 value="60"/>
  <seqNote1 value="62"/>
  <seqNote2 value="64"/>
  <seqNote3 value="65"/>
  <seqNote4 value="67"/>
  <seqNote5 value="69"/>
  <seqNote6 value="71"/>
  <seqNote7 value="72"/>
  <seqStepActive0 value="1"/>
  <seqStepActive1 value="1"/>
  <seqStepActive2 value="1"/>
  <seqStepActive3 value="1"/>
  <seqStepActive4 value="1"/>
  <seqStepActive5 value="1"/>
  <seqStepActive6 value="1"/>
  <seqStepActive7 value="1"/>
  <seqRandomMin value="0"/>
  <seqRandomMax value="127"/>
  <delWet value="0.70973438024520874023"/>
  <delFeed value="0.14770303666591644287"/>
  <delTime value="545.45452880859375"/>
  <delSync value="1"/>
  <delDivd value="1"/>
  <delDivs value="4"/>
  <delCut value="9372"/>
  <delRes value="0"/>
  <delTrip value="0"/>
  <delDot value="0"/>
  <delRec value="0"/>
  <delRev value="0"/>
  <delayActivation value="1"/>
  <syncToggle value="0"/>
  <freq value="440"/>
  <masterAmp value="-6"/>
  <masterPan value="0.45072114467620849609"/>
  <chorActivation value="1"/>
  <chorActivation value="1"/>
  <chorWidth value="0.065899297595024108887"/>
  <ChorAmount value="0.32556250691413879395"/>
  <ChorDepth value="11.073985099792480469"/>
  <chorRate value="0.33493125438690185547"/>
  <lowFiActivation value="1"/>
  <nBitsLowFi value="5.3778905868530273438"/>
  <clippingActivation value="0"/>
  <clippingFactor value="0"/>
  <oscSection value="0"/>
  <envSection value="0"/>
  <lfoSection value="0"/>
  <filterSection value="0"/>
  <fxSection value="0"/>
  <seqSection value="1"/>
</patch>
